labs/lab2_2/grayscale/rgb565GrayscaleIse.v
module rgb565GrayscaleIse # (parameter [7:0] customInstructionId = 8'd0)
                            (input wire         start,
                             input wire [31:0]  valueA,
                             input wire [7:0]   iseId,
                             output wire        done,
                             output wire [31:0] result);

    wire [15:0] R, G, B;
    wire [15:0] partialR1, partialR2, partialR3, partialR4;
    wire [15:0] partialG1, partialG2, partialG3, partialG4, partialG5;
    wire [15:0] partialB1, partialB2;
    wire [31:0] grayscale;

    // R values - 5 bit
    assign R = valueA[15:11] << 3;

    // G values - 6 bit
    assign G = valueA[10:5] << 2;

    // B values - 5 bit
    assign B = valueA[4:0] << 3;


    // Red multiplication
    assign partialR1 = R << 5;
    assign partialR2 = R << 4;
    assign partialR3 = R << 2;
    assign partialR4 = R << 1;

    // Green multiplication
    assign partialG1 = G << 7;
    assign partialG2 = G << 5;
    assign partialG3 = G << 4;
    assign partialG4 = G << 2;
    assign partialG5 = G << 1;

    // Blue multiplication
    assign partialB1 = B << 4;
    assign partialB2 = B << 1;

    // Grayscale conversion
    assign grayscale = (partialR1 + partialR2 + partialR3 + partialR4 + 
                        partialG1 + partialG2 + partialG3 + partialG4 + partialG5 + G + 
                        partialB1 + partialB2 + B) >> 8;
    
    // Output
    assign done = (iseId == customInstructionId) ? start : 1'b0;
    assign result = done ? (grayscale & 32'h000000FF) : 32'b0;

endmodule

labs/lab2_2/grayscale/rgb_tb.v
`timescale 1ps/1ps // set the time-units for simulation

module rgb565GrayscaleIse_tb;

    reg start, clock;
    reg [7:0] ciN;
    reg [31:0] valueA = 32'h00000000;
    wire [31:0] result;

    initial begin
        clock = 1'b0; // set the initial values
        repeat (4) #5 clock = ~clock; // generate 2 clock periods
        forever #5 clock = ~clock; // generate a clock with a period of 10 time-units
    end

    // instantiate the unit under test (UUT)
    rgb565GrayscaleIse #(.customInstructionId(8'h0B)) DUT (
        .start(start), 
        .valueA(valueA), 
        .iseId(ciN),
        .done(), 
        .result(result)
    );

    initial begin

        // Start the conversion
        start = 1'b1;
        valueA = 32'd33296;
        ciN = 8'h0B;
        @(negedge clock); /* wait for the reset period to end */
        repeat(2) @(negedge clock); /* wait for 2 clock cycles */
        $display("r = 16, g = 16, b = 16 ==> q = %d, theretical = 16",result);
        start = 1'b0;
        valueA = 32'h00000000;
        repeat(2) @(negedge clock); /* wait for 2 clock cycles */


        // Start the conversion
        start = 1'b1;
        valueA = 32'd20980;
        ciN = 8'h0B;
        @(negedge clock); /* wait for the reset period to end */
        repeat(2) @(negedge clock); /* wait for 2 clock cycles */
        $display("r = 10, g = 15, b = 20 ==> q =%d, theretical = 14",result);
        start = 1'b0;
        valueA = 32'h00000000;
        repeat(2) @(negedge clock); /* wait for 2 clock cycles */


        // Start the conversion
        start = 1'b1;
        valueA = 32'd64511;
        ciN = 8'h0B;
        @(negedge clock); /* wait for the reset period to end */
        repeat(2) @(negedge clock); /* wait for 2 clock cycles */
        $display("r = 31, g = 31, b = 31 ==> q = %d, theretical = 31",result);
        start = 1'b0;
        valueA = 32'h00000000;
        repeat(2) @(negedge clock); /* wait for 2 clock cycles */

        
        // Start the conversion
        start = 1'b1;
        valueA = 32'd12642;
        ciN = 8'h0B;
        @(negedge clock); /* wait for the reset period to end */
        repeat(2) @(negedge clock); /* wait for 2 clock cycles */
        $display("r = 6, g = 11, b = 2 ==> q = %d, theretical = 9",result);
        start = 1'b0;
        valueA = 32'h00000000;
        repeat(2) @(negedge clock); /* wait for 2 clock cycles */
        
        $finish;
    end

    initial begin
        // define the name of the .vcd file that can be viewed by GTKWAVE
        $dumpfile("grayscale.vcd"); 
        
        // dump all signals inside the DUT-component in the .vcd file
        $dumpvars(1, DUT); 
    end


endmodule

labs/lab2_2/grayscale/grayscale.vcd
$date
	Tue Mar 19 14:28:51 2024
$end
$version
	Icarus Verilog
$end
$timescale
	1ps
$end
$scope module rgb565GrayscaleIse_tb $end
$scope module DUT $end
$var wire 8 ! iseId [7:0] $end
$var wire 1 " start $end
$var wire 32 # valueA [31:0] $end
$var wire 32 $ result [31:0] $end
$var wire 16 % partialR4 [15:0] $end
$var wire 16 & partialR3 [15:0] $end
$var wire 16 ' partialR2 [15:0] $end
$var wire 16 ( partialR1 [15:0] $end
$var wire 16 ) partialG5 [15:0] $end
$var wire 16 * partialG4 [15:0] $end
$var wire 16 + partialG3 [15:0] $end
$var wire 16 , partialG2 [15:0] $end
$var wire 16 - partialG1 [15:0] $end
$var wire 16 . partialB2 [15:0] $end
$var wire 16 / partialB1 [15:0] $end
$var wire 32 0 grayscale [31:0] $end
$var wire 1 1 done $end
$var wire 16 2 R [15:0] $end
$var wire 16 3 G [15:0] $end
$var wire 16 4 B [15:0] $end
$var parameter 8 5 customInstructionId $end
$upscope $end
$upscope $end
$enddefinitions $end
$comment Show the parameter values. $end
$dumpall
b1011 5
$end
#0
$dumpvars
b10000000 4
b1000000 3
b10000000 2
11
b1010010 0
b100000000000 /
b100000000 .
b10000000000000 -
b100000000000 ,
b10000000000 +
b100000000 *
b10000000 )
b1000000000000 (
b100000000000 '
b1000000000 &
b100000000 %
b1010010 $
b1000001000010000 #
1"
b1011 !
$end
#30
b0 (
b0 '
b0 &
b0 %
b0 -
b0 ,
b0 +
b0 *
b0 )
b0 /
b0 .
b0 0
b0 2
b0 3
b0 4
b0 $
01
b0 #
0"
#50
b1000111 $
b1000111 0
b101000000000 (
b10100000000 '
b101000000 &
b10100000 %
b1111000000000 -
b11110000000 ,
b1111000000 +
b11110000 *
b1111000 )
b101000000000 /
b101000000 .
b1010000 2
b111100 3
b10100000 4
11
b101000111110100 #
1"
#80
b0 (
b0 '
b0 &
b0 %
b0 -
b0 ,
b0 +
b0 *
b0 )
b0 0
b0 /
b0 .
b0 2
b0 3
b0 4
b0 $
01
b0 #
0"
#100
b10011111 $
b1111100000000 (
b111110000000 '
b1111100000 &
b111110000 %
b11111000000000 -
b111110000000 ,
b11111000000 +
b111110000 *
b11111000 )
b10011111 0
b111110000000 /
b111110000 .
b11111000 2
b1111100 3
b11111000 4
11
b1111101111111111 #
1"
#130
b0 (
b0 '
b0 &
b0 %
b0 -
b0 ,
b0 +
b0 *
b0 )
b0 /
b0 .
b0 0
b0 2
b0 3
b0 4
b0 $
01
b0 #
0"
#150
b101010 $
b101010 0
b11000000000 (
b1100000000 '
b11000000 &
b1100000 %
b1011000000000 -
b10110000000 ,
b1011000000 +
b10110000 *
b1011000 )
b100000000 /
b100000 .
b110000 2
b101100 3
b10000 4
11
b11000101100010 #
1"
#180
b0 0
b0 (
b0 '
b0 &
b0 %
b0 -
b0 ,
b0 +
b0 *
b0 )
b0 /
b0 .
b0 2
b0 3
b0 4
b0 $
01
b0 #
0"
