labs/lab2_1/hand_in/virtual_prototype/systems/singleCore/verilog/counter.v
module counter #( parameter WIDTH = 8)
                ( input wire reset,
                             clock,
                             enable,
                             direction, /* a 1 is counting up, a 0 is counting down */
                  output reg [WIDTH-1:0] counterValue);

  always @(posedge clock)
    counterValue <= (reset == 1'b1) ? {WIDTH{1'b0}} : 
                    (enable == 1'b0) ? counterValue :
                    (direction == 1'b1) ? counterValue + 1 : counterValue - 1;
endmodule

labs/lab1/profiler_verilog/profileCi.v
/*
Verilog description for the profilerCi module
*/

module profileCi   #(parameter [7:0] customId = 8'h0B)
                    (input wire         start, 
                                        clock, 
                                        reset, 
                                        stall, 
                                        busIdle,
                     input wire [31:0]  valueA, 
                                        valueB,
                     input wire [7:0]   ciN,
                     output wire        done,
                     output wire [31:0] result);

    // Counter values
    wire [31:0] s_valCounter0, s_valCounter1, s_valCounter2, s_valCounter3;
    wire [31:0] outputCounters;

    // Counter enable signals
    wire s_enCounter0, s_enCounter1, s_enCounter2, s_enCounter3;
    reg r_enCounter0, r_enCounter1, r_enCounter2, r_enCounter3;

    // Counter reset signals
    wire s_resetCounter0, s_resetCounter1, s_resetCounter2, s_resetCounter3;

    // Define the control signals
    assign s_resetCounter0 = reset | (valueB[8] & done);
    assign s_resetCounter1 = reset | (valueB[9] & done);
    assign s_resetCounter2 = reset | (valueB[10] & done);
    assign s_resetCounter3 = reset | (valueB[11] & done);

    assign s_enCounter0 = r_enCounter0;
    assign s_enCounter1 = r_enCounter1 & stall;
    assign s_enCounter2 = r_enCounter2 & busIdle;
    assign s_enCounter3 = r_enCounter3;

    // Send the counter values to the output and generate the done signal
    assign outputCounters = valueA[1] ? (valueA[0] ? s_valCounter3 : s_valCounter2) : (valueA[0] ? s_valCounter1 : s_valCounter0);

    assign done = (ciN == customId) && start;
    assign result = done ? outputCounters : 32'h00000000;

    // Define the 4 counters
    counter #(.WIDTH(32)) counter0 ( .reset(s_resetCounter0), .clock(clock), .enable(s_enCounter0), .direction(1'b1), .counterValue(s_valCounter0) );
    counter #(.WIDTH(32)) counter1 ( .reset(s_resetCounter1), .clock(clock), .enable(s_enCounter1), .direction(1'b1), .counterValue(s_valCounter1) );
    counter #(.WIDTH(32)) counter2 ( .reset(s_resetCounter2), .clock(clock), .enable(s_enCounter2), .direction(1'b1), .counterValue(s_valCounter2) );
    counter #(.WIDTH(32)) counter3 ( .reset(s_resetCounter3), .clock(clock), .enable(s_enCounter3), .direction(1'b1), .counterValue(s_valCounter3) );

    // Update the enable signals
    always @(posedge clock) begin
        if (valueB[4] && done) 
            r_enCounter0 <= 1'b0;
        else if (valueB[0] && done) 
            r_enCounter0 <= 1'b1;

        if (valueB[5] && done) 
            r_enCounter1 <= 1'b0;
        else if (valueB[1] && done) 
            r_enCounter1 <= 1'b1;

        if (valueB[6] && done) 
            r_enCounter2 <= 1'b0;
        else if (valueB[2] && done) 
            r_enCounter2 <= 1'b1;

        if (valueB[7] && done) 
            r_enCounter3 <= 1'b0;
        else if (valueB[3] && done) 
            r_enCounter3 <= 1'b1;
    end


endmodule

labs/lab2_1/profiler_verilog/test_profiler.v
`timescale 1ps/1ps // set the time-units for simulation

module profileCi_tb;

    reg start, clock, reset, stall, busIdle;
    reg [7:0] ciN;
    reg [31:0] valueA = 32'h00000000;
    reg [31:0] valueB = 32'h00000000;
    wire [31:0] result;

    initial begin
        reset = 1'b1;
        clock = 1'b0; // set the initial values
        repeat (4) #5 clock = ~clock; // generate 2 clock periods
        reset = 1'b0; // de-activate the reset
        forever #5 clock = ~clock; // generate a clock with a period of 10 time-units
    end

    profileCi #(.customId(8'h0B)) DUT (
        .start(start), 
        .clock(clock), 
        .reset(reset), 
        .stall(stall), 
        .busIdle(busIdle),
        .valueA(valueA), 
        .valueB(valueB),
        .ciN(ciN),
        .done(), 
        .result(result)
    );

    initial begin

        // Initialize the inputs
        //start = 1'b0;
        ciN = 8'h0B;
        busIdle = 1'b1;
        stall = 1'b1;
        @(negedge reset); /* wait for the reset period to end */
        repeat(2) @(negedge clock); /* wait for 2 clock cycles */
        #5

        // Activate counter 0
        valueB = 32'h00000001;
        start = 1'b1;
        @(posedge clock); /* wait for the next clock cycle */
        //start = 1'b0;
        //valueB = 32'h00000000;
        @(posedge clock); /* wait for 2 clock cycles */


        // Read the result
        start = 1'b1;
        @(posedge clock); /* wait for the next clock cycle */
        //start = 1'b0;
        
        @(posedge clock); /* wait for the next clock cycle */
        ciN = 8'h0C;
        repeat(2) @(posedge clock); /* wait for 5 clock cycles */
        start = 1'b1;
        valueB = 32'h00000003;
        @(posedge clock); /* wait for the next clock cycle */
        ciN = 8'h0B;
        repeat(2) @(posedge clock); /* wait for 5 clock cycles */


        // Disable counter 0
        valueB = 32'h00000011;
        start = 1'b1;
        @(posedge clock); /* wait for the next clock cycle */
        //start = 1'b0;
        valueB = 32'h00000000;

        repeat(2) @(posedge clock); /* wait for 5 clock cycles */

        // Reset counter 0
        // valueB = 32'h00000100;
        // start = 1'b1;
        // @(posedge clock); /* wait for the next clock cycle */
        // //start = 1'b0;
        // valueB = 32'h00000000;
        
        repeat(2) @(posedge clock); /* wait for 5 clock cycles */

        // Activate counter 1
        valueB = 32'h00000002;
        start = 1'b1;
        @(posedge clock); /* wait for the next clock cycle */
        //start = 1'b0;
        valueB = 32'h00000000;
        @(posedge clock); /* wait for 2 clock cycles */

        repeat(2) @(posedge clock); /* wait for 5 clock cycles */

        // Reset stall
        stall = 1'b0;

        repeat(2) @(posedge clock); /* wait for 5 clock cycles */

        // Activate counter 0, 2 and 3
        valueB = 32'h000000D;
        start = 1'b1;
        @(posedge clock); /* wait for the next clock cycle */
        //start = 1'b0;
        valueB = 32'h00000000;

        repeat(2) @(posedge clock); /* wait for 5 clock cycles */

        $finish; /* finish the simulation */
    end
    
    initial begin
        // define the name of the .vcd file that can be viewed by GTKWAVE
        $dumpfile("profiler.vcd"); 
        
        // dump all signals inside the DUT-component in the .vcd file
        $dumpvars(1, DUT); 
    end

endmodule

labs/lab2_1/profiler_verilog/profiler.vcd
$date
	Mon Mar 18 20:32:26 2024
$end
$version
	Icarus Verilog
$end
$timescale
	1ps
$end
$scope module profileCi_tb $end
$scope module DUT $end
$var wire 1 ! busIdle $end
$var wire 8 " ciN [7:0] $end
$var wire 1 # clock $end
$var wire 1 $ done $end
$var wire 1 % reset $end
$var wire 1 & s_enCounter0 $end
$var wire 1 ' s_enCounter1 $end
$var wire 1 ( s_enCounter2 $end
$var wire 1 ) s_enCounter3 $end
$var wire 1 * s_resetCounter0 $end
$var wire 1 + s_resetCounter1 $end
$var wire 1 , s_resetCounter2 $end
$var wire 1 - s_resetCounter3 $end
$var wire 1 . stall $end
$var wire 1 / start $end
$var wire 32 0 valueA [31:0] $end
$var wire 32 1 valueB [31:0] $end
$var wire 32 2 s_valCounter3 [31:0] $end
$var wire 32 3 s_valCounter2 [31:0] $end
$var wire 32 4 s_valCounter1 [31:0] $end
$var wire 32 5 s_valCounter0 [31:0] $end
$var wire 32 6 result [31:0] $end
$var wire 32 7 outputCounters [31:0] $end
$var parameter 8 8 customId $end
$var reg 1 9 r_enCounter0 $end
$var reg 1 : r_enCounter1 $end
$var reg 1 ; r_enCounter2 $end
$var reg 1 < r_enCounter3 $end
$upscope $end
$upscope $end
$enddefinitions $end
$comment Show the parameter values. $end
$dumpall
b1011 8
$end
#0
$dumpvars
x<
x;
x:
x9
bx 7
bx 6
bx 5
bx 4
bx 3
bx 2
b0 1
b0 0
x/
1.
1-
1,
1+
1*
x)
x(
x'
x&
1%
x$
0#
b1011 "
1!
$end
#5
b0 6
b0 7
b0 5
b0 4
b0 3
b0 2
1#
#10
0#
#15
1#
#20
0*
0+
0,
0-
0%
0#
#25
b0x 6
b0x 7
b0x 5
b0x 4
b0x 3
b0x 2
1#
#30
0#
#35
bx 6
bx 7
bx 2
bx 3
bx 4
bx 5
1#
#40
0#
#45
1$
1/
b1 1
1#
#50
0#
#55
1&
19
1#
#60
0#
#65
1#
#70
0#
#75
1#
#80
0#
#85
b0 6
0$
b1100 "
1#
#90
0#
#95
1#
#100
0#
#105
b11 1
1#
#110
0#
#115
bx 6
1$
b1011 "
1#
#120
0#
#125
1'
1:
1#
#130
0#
#135
b10001 1
1#
#140
0#
#145
b0 1
1#
#150
0#
#155
1#
#160
0#
#165
1#
#170
0#
#175
1#
#180
0#
#185
b10 1
1#
#190
0#
#195
b0 1
1#
#200
0#
#205
1#
#210
0#
#215
1#
#220
0#
#225
0'
0.
1#
#230
0#
#235
1#
#240
0#
#245
1(
1)
1<
1;
b1101 1
1#
#250
0#
#255
b0 1
1#
